autonml/__init__.py
autonml/auto_solutions.py
autonml/autonml_api.py
autonml/core_pb2.py
autonml/core_pb2_grpc.py
autonml/create_d3m_dataset.py
autonml/default_hyperparams.py
autonml/helper_functions.py
autonml/main.py
autonml/mkpline.py
autonml/pipeline_pb2.py
autonml/pipeline_pb2_grpc.py
autonml/primitive_lib.py
autonml/primitive_pb2.py
autonml/primitive_pb2_grpc.py
autonml/primitivedescription.py
autonml/problem_pb2.py
autonml/problem_pb2_grpc.py
autonml/search.py
autonml/solution_templates.py
autonml/solutiondescription.py
autonml/util.py
autonml/value_pb2.py
autonml/value_pb2_grpc.py
autonml/api_v3/__init__.py
autonml/api_v3/core.py
autonml/static/__init__.py
autonml-0.3.3.dist-info/LICENSE
autonml-0.3.3.dist-info/METADATA
autonml-0.3.3.dist-info/NOTICE.md
autonml-0.3.3.dist-info/WHEEL
autonml-0.3.3.dist-info/entry_points.txt
autonml-0.3.3.dist-info/top_level.txt
autonml-0.3.3.dist-info/RECORD
