Metadata-Version: 2.1
Name: autonml
Version: 0.3.3
Summary: AutonML : CMU's AutoML System
Home-page: https://gitlab.com/autonlab/d3m/autonml/-/tree/dev
Author: Saswati Ray, Andrew Williams, Vedant Sanil
Maintainer: Andrew Williams, Vedant Sanil
Maintainer-email: awillia2@andrew.cmu.edu, vsanil@andrew.cmu.edu
License: Apache-2.0
Keywords: datadrivendiscovery,automl,d3m,ta2,cmu
Classifier: Development Status :: 3 - Alpha
Classifier: License :: OSI Approved :: Apache Software License
Classifier: Topic :: Scientific/Engineering
Requires-Python: >=3.6
License-File: LICENSE
License-File: NOTICE.md
Requires-Dist: Cython
Requires-Dist: SQLAlchemy (<1.4,>=1.2)
Requires-Dist: datamart-materialize (<0.10,>=0.9)
Requires-Dist: datamart-profiler (<0.10,>=0.9)
Requires-Dist: nltk
Requires-Dist: numpy
Requires-Dist: pandas
Requires-Dist: scipy
Requires-Dist: smac (<0.14,>=0.13)
Requires-Dist: ConfigSpace (<0.5,>=0.4.19)
Requires-Dist: scikit-learn (==0.22.2.post1)
Requires-Dist: scikit-image (==0.17.2)
Requires-Dist: torch (>=1.7)
Requires-Dist: PyYAML
Requires-Dist: mxnet
Requires-Dist: opencv-python
Requires-Dist: d3m
Requires-Dist: d3m-automl-rpc
